mcp_asset_generator/__init__.py
mcp_asset_generator/main.py
mcp_asset_generator-0.1.0.dist-info/METADATA
mcp_asset_generator-0.1.0.dist-info/WHEEL
mcp_asset_generator-0.1.0.dist-info/top_level.txt
mcp_asset_generator-0.1.0.dist-info/RECORD
