Metadata-Version: 2.4
Name: mcp-asset_generator
Version: 0.1.0
Summary: Builds supplemental UI, helper scripts, and resource files for use in client apps like Theia, Cursor, or TypingMind with visual rendering of tools, resources, and prompts
Home-page: https://github.com/Sumedh99/mcp_asset_generator
Author: Sumedh99
Author-email: Sumedh99@users.noreply.github.com
Classifier: Programming Language :: Python :: 3
Classifier: License :: OSI Approved :: MIT License
Classifier: Operating System :: OS Independent
Requires-Python: >=3.7
Dynamic: author
Dynamic: author-email
Dynamic: classifier
Dynamic: description
Dynamic: description-content-type
Dynamic: home-page
Dynamic: requires-python
Dynamic: summary
